{"version":1,"resource":"file:///home/devilunraveled/Projects/DASS/Product%20Labs/DASS2k23-Team-5/backend/socketControllers/TranscriptEvents.js","entries":[{"id":"EoXh.js","timestamp":1681893112265},{"id":"t5Po.js","timestamp":1681893260113},{"id":"MtM9.js","timestamp":1681893772593},{"id":"SW1e.js","timestamp":1681896231953},{"id":"5tOW.js","timestamp":1681896460365},{"id":"ewmu.js","timestamp":1681897090460},{"id":"XSyN.js","timestamp":1681897284815},{"id":"KFVn.js","timestamp":1681917721875},{"id":"JRNk.js","timestamp":1681918854736},{"id":"rtfa.js","timestamp":1682007718978},{"id":"SOCD.js","timestamp":1682248198120},{"id":"8BHZ.js","timestamp":1682248221218},{"id":"Xhyh.js","timestamp":1682249340007},{"id":"027L.js","timestamp":1682249531020},{"id":"ykjM.js","timestamp":1682249569850},{"id":"WfgU.js","timestamp":1682249750746},{"id":"MYqq.js","timestamp":1682250457851},{"id":"MyIM.js","timestamp":1682252901616},{"id":"w4jA.js","timestamp":1682342065966},{"id":"U9Pv.js","timestamp":1682342805891},{"id":"19r8.js","timestamp":1682342922625},{"id":"zyle.js","timestamp":1682342949414},{"id":"AmWP.js","timestamp":1682361894867}]}